ndelement-0.3.0.dist-info/METADATA
ndelement-0.3.0.dist-info/WHEEL
ndelement-0.3.0.dist-info/licenses/LICENSE
ndelement/__init__.py
ndelement/_ndelementrs/__init__.py
ndelement/_ndelementrs/ffi.py
ndelement/_ndelementrs/lib_ndelementrs.dylib
ndelement/ciarlet.py
ndelement/polynomials.py
ndelement/quadrature.py
ndelement/reference_cell.py
ndelement-0.3.0.dist-info/RECORD
