Metadata-Version: 2.4
Name: ndelement
Version: 0.3.0
Classifier: Programming Language :: Rust
Classifier: Programming Language :: Python :: Implementation :: CPython
Requires-Dist: maturin>=1.7.2
Requires-Dist: numpy
Requires-Dist: cffi
Requires-Dist: pytest
Requires-Dist: pip
Requires-Dist: patchelf ; platform_system == 'Linux'
License-File: LICENSE
Summary: n-dimensional finite element definition library.
Keywords: numerics
Home-Page: https://github.com/bempp/ndelement
Author: Matthew Scroggs <rust@mscroggs.co.uk>
Author-email: Matthew Scroggs <rust@mscroggs.co.uk>
License: BSD-3-Clause
Requires-Python: >=3.8
Project-URL: homepage, https://github.com/bempp/ndelement
Project-URL: repository, https://github.com/bempp/ndelement
